episimlab/__init__.py
episimlab/compt_model.py
episimlab/foi.py
episimlab/models/__init__.py
episimlab/models/epi_model.py
episimlab/models/example_sir.py
episimlab/models/example_sirv.py
episimlab/models/partition_v1.py
episimlab/models/vaccine.py
episimlab/partition/__init__.py
episimlab/partition/contacts.py
episimlab/partition/partition.py
episimlab/partition/travel_pat.py
episimlab/setup/__init__.py
episimlab/setup/coords.py
episimlab/setup/greek/__init__.py
episimlab/setup/greek/eta.py
episimlab/setup/greek/gamma.py
episimlab/setup/greek/mu.py
episimlab/setup/greek/nu.py
episimlab/setup/greek/rho.py
episimlab/setup/greek/sigma.py
episimlab/setup/greek/tau.py
episimlab/setup/seed.py
episimlab/setup/state.py
episimlab/setup/sto.py
episimlab/utils/__init__.py
episimlab/utils/datetime.py
episimlab/utils/plot.py
episimlab/utils/rng.py
episimlab/utils/tags.py
episimlab/utils/variable.py
episimlab-2.2.2.dist-info/LICENSE.md
episimlab-2.2.2.dist-info/WHEEL
episimlab-2.2.2.dist-info/METADATA
episimlab-2.2.2.dist-info/RECORD
